classnames/__init__.py
classnames/classnames.py
classnames-0.1.0.dist-info/AUTHORS.rst
classnames-0.1.0.dist-info/LICENSE
classnames-0.1.0.dist-info/METADATA
classnames-0.1.0.dist-info/WHEEL
classnames-0.1.0.dist-info/top_level.txt
classnames-0.1.0.dist-info/RECORD
