Metadata-Version: 2.1
Name: classnames
Version: 0.1.0
Summary: Utility to create CSS class strings from a multitude of values without poking around with string templates and lengthy logic.
Home-page: https://github.com/lucafaggianelli/python-classnames
Author: Luca Faggianelli
Author-email: luca.faggianelli@gmail.com
License: MIT license
Keywords: classnames
Classifier: Development Status :: 2 - Pre-Alpha
Classifier: Intended Audience :: Developers
Classifier: License :: OSI Approved :: MIT License
Classifier: Natural Language :: English
Classifier: Programming Language :: Python :: 3
Classifier: Programming Language :: Python :: 3.6
Classifier: Programming Language :: Python :: 3.7
Classifier: Programming Language :: Python :: 3.8
Requires-Python: >=3.6
License-File: LICENSE
License-File: AUTHORS.rst
